celldeath/__init__.py
celldeath/main.py
celldeath/predict.py
celldeath/slicer.py
celldeath/train.py
celldeath/utils.py
celldeath-0.9.17.dist-info/LICENSE
celldeath-0.9.17.dist-info/METADATA
celldeath-0.9.17.dist-info/WHEEL
celldeath-0.9.17.dist-info/entry_points.txt
celldeath-0.9.17.dist-info/top_level.txt
celldeath-0.9.17.dist-info/RECORD
