Metadata-Version: 2.1
Name: celldeath
Version: 0.9.17
Summary: A tool to identify cell death based on deep learning
Home-page: https://github.com/sgmiriuka/celldeath
Author: Santiago Miriuka, Alejandro La Greca, Nelba Pérez
Author-email: smiriuka@fleni.org.ar, ale.lagreca@gmail.com, nelbap@hotmail.com
License: UNKNOWN
Platform: UNKNOWN
Classifier: Development Status :: 4 - Beta
Classifier: Programming Language :: Python :: 3
Classifier: License :: OSI Approved :: MIT License
Classifier: Operating System :: OS Independent
Classifier: Topic :: Scientific/Engineering :: Medical Science Apps.
Requires-Python: >=3.6
Requires-Dist: fastai (>=1.0.60)
Requires-Dist: image-slicer (==0.3.0)
Requires-Dist: matplotlib (>=3.1.1)
